[{"code": "P142", "value": "N Djamena", "coordinates": {"lat": 12.1348457, "lng": 15.0557415}}, {"code": "P142", "value": "N'Djamena", "coordinates": {"lat": 12.1348457, "lng": 15.0557415}}, {"code": "abidjan", "value": "Abidjan", "coordinates": {"lat": 5.3599517, "lng": -4.0082563}}, {"code": "P2", "value": "Abu Dhabi", "coordinates": {"lat": 24.453884, "lng": 54.3773438}}, {"code": "P3", "value": "Abuja", "coordinates": {"lat": 9.0764785, "lng": 7.398574}}, {"code": "P4", "value": "Accra", "coordinates": {"lat": 5.6037168, "lng": -0.1869644}}, {"code": "adana", "value": "Adana", "coordinates": {"lat": 36.9914194, "lng": 35.3308285}}, {"code": "P5", "value": "Addis Ababa", "coordinates": {"lat": 8.9806034, "lng": 38.7577605}}, {"code": "P6", "value": "Algiers", "coordinates": {"lat": 36.753768, "lng": 3.0587561}}, {"code": "P7", "value": "Almaty", "coordinates": {"lat": 43.2220146, "lng": 76.8512485}}, {"code": "P8", "value": "Amman", "coordinates": {"lat": 31.9539494, "lng": 35.910635}}, {"code": "P9", "value": "Amsterdam", "coordinates": {"lat": 52.3675734, "lng": 4.9041389}}, {"code": "P10", "value": "Ankara", "coordinates": {"lat": 39.9333635, "lng": 32.8597419}}, {"code": "P11", "value": "Antananarivo", "coordinates": {"lat": -18.8791902, "lng": 47.5079055}}, {"code": "P225", "value": "Apia", "coordinates": {"lat": -13.8506958, "lng": -171.7513551}}, {"code": "P12", "value": "Ashgabat", "coordinates": {"lat": 37.9600766, "lng": 58.32606289999999}}, {"code": "P13", "value": "Asmara", "coordinates": {"lat": 15.3228767, "lng": 38.9250517}}, {"code": "astana", "value": "Astana", "coordinates": {"lat": 51.16052269999999, "lng": 71.4703558}}, {"code": "P15", "value": "Asuncion", "coordinates": {"lat": -25.2637399, "lng": -57.57592599999999}}, {"code": "athens", "value": "Athens", "coordinates": {"lat": 37.9838096, "lng": 23.7275388}}, {"code": "P17", "value": "Auckland", "coordinates": {"lat": -36.85088270000001, "lng": 174.7644881}}, {"code": "P226", "value": "Baghdad", "coordinates": {"lat": 33.315241, "lng": 44.3660671}}, {"code": "P19", "value": "Baku", "coordinates": {"lat": 40.40926169999999, "lng": 49.8670924}}, {"code": "P20", "value": "Bamako", "coordinates": {"lat": 12.6392316, "lng": -8.0028892}}, {"code": "P21", "value": "Bandar Seri Begawan", "coordinates": {"lat": 4.903052199999999, "lng": 114.939821}}, {"code": "P22", "value": "Bangkok", "coordinates": {"lat": 13.7563309, "lng": 100.5017651}}, {"code": "banjul", "value": "Banjul", "coordinates": {"lat": 13.454375, "lng": -16.5753186}}, {"code": "barcelona", "value": "Barcelona", "coordinates": {"lat": 41.3873974, "lng": 2.168568}}, {"code": "P24", "value": "Beijing", "coordinates": {"lat": 39.904211, "lng": 116.407395}}, {"code": "P25", "value": "Beirut", "coordinates": {"lat": 33.8937913, "lng": 35.5017767}}, {"code": "P26", "value": "Belfast", "coordinates": {"lat": 54.59728500000001, "lng": -5.93012}}, {"code": "P27", "value": "Belgrade", "coordinates": {"lat": 44.8125449, "lng": 20.46123}}, {"code": "P28", "value": "Belmopan", "coordinates": {"lat": 17.2510114, "lng": -88.7590201}}, {"code": "P29", "value": "Berlin", "coordinates": {"lat": 52.52000659999999, "lng": 13.404954}}, {"code": "P30", "value": "Bern", "coordinates": {"lat": 46.9479739, "lng": 7.4474468}}, {"code": "P31", "value": "Bishkek", "coordinates": {"lat": 42.8746212, "lng": 74.5697617}}, {"code": "P32", "value": "Bogota", "coordinates": {"lat": 4.710988599999999, "lng": -74.072092}}, {"code": "P33", "value": "Brasilia", "coordinates": {"lat": -15.7975154, "lng": -47.89188739999999}}, {"code": "P34", "value": "Bratislava", "coordinates": {"lat": 48.1485965, "lng": 17.1077477}}, {"code": "P35", "value": "Brazzaville", "coordinates": {"lat": -4.2633597, "lng": 15.2428853}}, {"code": "P36", "value": "Bridgetown", "coordinates": {"lat": 13.1059816, "lng": -59.61317409999999}}, {"code": "P37", "value": "Brussels", "coordinates": {"lat": 50.8476424, "lng": 4.3571696}}, {"code": "P38", "value": "Bucharest", "coordinates": {"lat": 44.4267674, "lng": 26.1025384}}, {"code": "P39", "value": "Budapest", "coordinates": {"lat": 47.497912, "lng": 19.040235}}, {"code": "P40", "value": "Buenos Aires", "coordinates": {"lat": -34.6036844, "lng": -58.3815591}}, {"code": "P41", "value": "Bujumbura", "coordinates": {"lat": -3.361378, "lng": 29.3598782}}, {"code": "P42", "value": "Cairo", "coordinates": {"lat": 30.0444196, "lng": 31.2357116}}, {"code": "P43", "value": "Calgary", "coordinates": {"lat": 51.04473309999999, "lng": -114.0718831}}, {"code": "P44", "value": "Cape Town", "coordinates": {"lat": -33.9248685, "lng": 18.4240553}}, {"code": "P45", "value": "Caracas", "coordinates": {"lat": 10.4805937, "lng": -66.90360629999999}}, {"code": "P46", "value": "Casablanca", "coordinates": {"lat": 33.5731104, "lng": -7.589843399999999}}, {"code": "P47", "value": "Chengdu", "coordinates": {"lat": 30.5722599, "lng": 104.0665099}}, {"code": "P48", "value": "Chennai ( Madras)", "coordinates": {"lat": 13.0826802, "lng": 80.2707184}}, {"code": "P49", "value": "Chiang Mai", "coordinates": {"lat": 18.7883439, "lng": 98.98530079999999}}, {"code": "P50", "value": "Chisinau", "coordinates": {"lat": 47.0104529, "lng": 28.8638103}}, {"code": "P51", "value": "Ciudad Juarez", "coordinates": {"lat": 31.6903638, "lng": -106.4245478}}, {"code": "P52", "value": "Colombo", "coordinates": {"lat": 6.9270786, "lng": 79.861243}}, {"code": "P53", "value": "Conakry", "coordinates": {"lat": 9.641185499999999, "lng": -13.5784012}}, {"code": "P54", "value": "Copenhagen", "coordinates": {"lat": 55.6760968, "lng": 12.5683371}}, {"code": "P55", "value": "Cotonou", "coordinates": {"lat": 6.3702928, "lng": 2.3912362}}, {"code": "P223", "value": "Curacao", "coordinates": {"lat": 12.16957, "lng": -68.99002}}, {"code": "P56", "value": "Dakar", "coordinates": {"lat": 14.716677, "lng": -17.4676861}}, {"code": "P57", "value": "Damascus", "coordinates": {"lat": 33.5138073, "lng": 36.2765279}}, {"code": "P58", "value": "Dar Es Salaam", "coordinates": {"lat": -6.792354, "lng": 39.2083284}}, {"code": "P59", "value": "Dhahran", "coordinates": {"lat": 26.2361248, "lng": 50.0393017}}, {"code": "P60", "value": "Dhaka", "coordinates": {"lat": 23.810332, "lng": 90.4125181}}, {"code": "P227", "value": "Dili", "coordinates": {"lat": -8.5568557, "lng": 125.5603143}}, {"code": "P61", "value": "Djibouti", "coordinates": {"lat": 11.825138, "lng": 42.590275}}, {"code": "P62", "value": "Doha", "coordinates": {"lat": 25.2854473, "lng": 51.53103979999999}}, {"code": "P63", "value": "Dubai", "coordinates": {"lat": 25.2048493, "lng": 55.2707828}}, {"code": "P64", "value": "Dublin", "coordinates": {"lat": 53.3498053, "lng": -6.2603097}}, {"code": "P65", "value": "Durban", "coordinates": {"lat": -29.85868039999999, "lng": 31.0218404}}, {"code": "P66", "value": "Dushanbe", "coordinates": {"lat": 38.5597722, "lng": 68.7870384}}, {"code": "erbil", "value": "Erbil", "coordinates": {"lat": 36.190073, "lng": 43.9930303}}, {"code": "P67", "value": "Florence", "coordinates": {"lat": 43.7695604, "lng": 11.2558136}}, {"code": "P68", "value": "Frankfurt", "coordinates": {"lat": 50.1109221, "lng": 8.6821267}}, {"code": "P69", "value": "Freetown", "coordinates": {"lat": 8.4656765, "lng": -13.2317225}}, {"code": "fukuoka", "value": "Fukuoka", "coordinates": {"lat": 33.5901838, "lng": 130.4016888}}, {"code": "P70", "value": "Gaborone", "coordinates": {"lat": -24.6282079, "lng": 25.9231471}}, {"code": "P71", "value": "Georgetown", "coordinates": {"lat": 38.9097057, "lng": -77.06535650000001}}, {"code": "P72", "value": "Guadalajara", "coordinates": {"lat": 20.6596988, "lng": -103.3496092}}, {"code": "P73", "value": "Guangzhou", "coordinates": {"lat": 23.1290799, "lng": 113.26436}}, {"code": "P74", "value": "Guatemala City", "coordinates": {"lat": 14.6349149, "lng": -90.5068824}}, {"code": "P75", "value": "Guayaquil", "coordinates": {"lat": -2.1894128, "lng": -79.8890662}}, {"code": "P76", "value": "Halifax", "coordinates": {"lat": 44.6475811, "lng": -63.5727683}}, {"code": "P77", "value": "Hamilton", "coordinates": {"lat": 43.2557206, "lng": -79.8711024}}, {"code": "P78", "value": "Hanoi", "coordinates": {"lat": 21.0277644, "lng": 105.8341598}}, {"code": "P79", "value": "Harare", "coordinates": {"lat": -17.8216288, "lng": 31.0492259}}, {"code": "P80", "value": "Havana", "coordinates": {"lat": 23.1135925, "lng": -82.3665956}}, {"code": "P81", "value": "Helsinki", "coordinates": {"lat": 60.16985569999999, "lng": 24.938379}}, {"code": "P82", "value": "Hermosillo", "coordinates": {"lat": 29.0729673, "lng": -110.9559192}}, {"code": "P83", "value": "Ho Chi Minh City", "coordinates": {"lat": 10.8230989, "lng": 106.6296638}}, {"code": "P84", "value": "Hong Kong", "coordinates": {"lat": 22.3193039, "lng": 114.1693611}}, {"code": "P85", "value": "Hyderabad", "coordinates": {"lat": 17.385044, "lng": 78.486671}}, {"code": "P86", "value": "Islamabad", "coordinates": {"lat": 33.6844202, "lng": 73.04788479999999}}, {"code": "P87", "value": "Istanbul", "coordinates": {"lat": 41.0082376, "lng": 28.9783589}}, {"code": "P88", "value": "Jakarta", "coordinates": {"lat": -6.2087634, "lng": 106.845599}}, {"code": "P89", "value": "Jeddah", "coordinates": {"lat": 21.485811, "lng": 39.19250479999999}}, {"code": "P90", "value": "Jerusalem", "coordinates": {"lat": 31.768319, "lng": 35.21371}}, {"code": "P91", "value": "Johannesburg", "coordinates": {"lat": -26.2041028, "lng": 28.0473051}}, {"code": "P228", "value": "Juba", "coordinates": {"lat": 4.859363, "lng": 31.57125}}, {"code": "P229", "value": "Kabul", "coordinates": {"lat": 34.5553494, "lng": 69.207486}}, {"code": "P93", "value": "Kampala", "coordinates": {"lat": 0.3475964, "lng": 32.5825197}}, {"code": "kaohsiung", "value": "Kaohsiung", "coordinates": {"lat": 22.6350591, "lng": 120.3355193}}, {"code": "P94", "value": "Karachi", "coordinates": {"lat": 24.8607343, "lng": 67.0011364}}, {"code": "P95", "value": "Kathmandu", "coordinates": {"lat": 27.7172453, "lng": 85.3239605}}, {"code": "P96", "value": "Khartoum", "coordinates": {"lat": 15.5006544, "lng": 32.5598994}}, {"code": "P97", "value": "Kigali", "coordinates": {"lat": -1.9440727, "lng": 30.0618851}}, {"code": "P98", "value": "Kingston", "coordinates": {"lat": 51.41233, "lng": -0.300689}}, {"code": "P99", "value": "Kinshasa", "coordinates": {"lat": -4.4419311, "lng": 15.2662931}}, {"code": "P100", "value": "Kolkata", "coordinates": {"lat": 22.572646, "lng": 88.36389500000001}}, {"code": "P101", "value": "Kolonia", "coordinates": {"lat": 50.937531, "lng": 6.9602786}}, {"code": "P102", "value": "Koror", "coordinates": {"lat": 7.3410628, "lng": 134.4771596}}, {"code": "P103", "value": "Krakow", "coordinates": {"lat": 50.06465009999999, "lng": 19.9449799}}, {"code": "P104", "value": "Kuala Lumpur", "coordinates": {"lat": 3.1569486, "lng": 101.712303}}, {"code": "P105", "value": "Kuwait", "coordinates": {"lat": 29.31166, "lng": 47.481766}}, {"code": "P106", "value": "Kyiv", "coordinates": {"lat": 50.4501, "lng": 30.5234}}, {"code": "P107", "value": "La Paz", "coordinates": {"lat": -16.489689, "lng": -68.11929359999999}}, {"code": "P108", "value": "Lagos", "coordinates": {"lat": 6.5243793, "lng": 3.3792057}}, {"code": "lahore", "value": "Lahore", "coordinates": {"lat": 31.5203696, "lng": 74.35874729999999}}, {"code": "P109", "value": "Libreville", "coordinates": {"lat": 0.4161976, "lng": 9.4672676}}, {"code": "P110", "value": "Lilongwe", "coordinates": {"lat": -13.9626121, "lng": 33.7741195}}, {"code": "P111", "value": "Lima", "coordinates": {"lat": -12.0463731, "lng": -77.042754}}, {"code": "P112", "value": "Lisbon", "coordinates": {"lat": 38.7222524, "lng": -9.1393366}}, {"code": "P113", "value": "Ljubljana", "coordinates": {"lat": 46.0569465, "lng": 14.5057515}}, {"code": "lome", "value": "Lome", "coordinates": {"lat": 6.1256261, "lng": 1.2254183}}, {"code": "P115", "value": "London", "coordinates": {"lat": 51.5072178, "lng": -0.1275862}}, {"code": "P116", "value": "Luanda", "coordinates": {"lat": -8.8146556, "lng": 13.2301756}}, {"code": "P117", "value": "Lusaka", "coordinates": {"lat": -15.3875259, "lng": 28.3228165}}, {"code": "P118", "value": "Luxembourg", "coordinates": {"lat": 49.815273, "lng": 6.129582999999999}}, {"code": "P119", "value": "Madrid", "coordinates": {"lat": 40.4167754, "lng": -3.7037902}}, {"code": "P120", "value": "Majuro", "coordinates": {"lat": 7.066667, "lng": 171.266667}}, {"code": "P121", "value": "Malabo", "coordinates": {"lat": 3.7549606, "lng": 8.7821344}}, {"code": "managua", "value": "Managua", "coordinates": {"lat": 12.1149926, "lng": -86.2361744}}, {"code": "P123", "value": "Manama", "coordinates": {"lat": 26.2235305, "lng": 50.5875935}}, {"code": "P124", "value": "Manila", "coordinates": {"lat": 14.5995124, "lng": 120.9842195}}, {"code": "P125", "value": "Maputo", "coordinates": {"lat": -25.969248, "lng": 32.5731746}}, {"code": "marseille", "value": "Marseille", "coordinates": {"lat": 43.296482, "lng": 5.36978}}, {"code": "P126", "value": "Maseru", "coordinates": {"lat": -29.3150767, "lng": 27.4869229}}, {"code": "P127", "value": "Matamoros", "coordinates": {"lat": 25.8690294, "lng": -97.50273759999999}}, {"code": "P128", "value": "Mbabane", "coordinates": {"lat": -26.3054482, "lng": 31.1366715}}, {"code": "P129", "value": "Melbourne", "coordinates": {"lat": -37.8136276, "lng": 144.9630576}}, {"code": "P130", "value": "Merida", "coordinates": {"lat": 20.9673702, "lng": -89.5925857}}, {"code": "P131", "value": "Mexico City", "coordinates": {"lat": 19.4326077, "lng": -99.133208}}, {"code": "P132", "value": "Milan", "coordinates": {"lat": 45.4642035, "lng": 9.189982}}, {"code": "P133", "value": "Minsk", "coordinates": {"lat": 53.9006011, "lng": 27.558972}}, {"code": "P134", "value": "Monrovia", "coordinates": {"lat": 6.3156068, "lng": -10.8073698}}, {"code": "P135", "value": "Monterrey", "coordinates": {"lat": 25.6866142, "lng": -100.3161126}}, {"code": "P136", "value": "Montevideo", "coordinates": {"lat": -34.9011127, "lng": -56.16453139999999}}, {"code": "P137", "value": "Montreal", "coordinates": {"lat": 45.5018869, "lng": -73.56739189999999}}, {"code": "P138", "value": "Moscow", "coordinates": {"lat": 55.755826, "lng": 37.6173}}, {"code": "P139", "value": "Mumbai (Bombay)", "coordinates": {"lat": 19.0759837, "lng": 72.8776559}}, {"code": "P140", "value": "Munich", "coordinates": {"lat": 48.1351253, "lng": 11.5819806}}, {"code": "P141", "value": "Muscat", "coordinates": {"lat": 23.5880307, "lng": 58.3828717}}, {"code": "P142", "value": "N`Djamena", "coordinates": {"lat": 12.1348457, "lng": 15.0557415}}, {"code": "P143", "value": "Naha", "coordinates": {"lat": 26.2125758, "lng": 127.6790208}}, {"code": "P144", "value": "Nairobi", "coordinates": {"lat": -1.2920659, "lng": 36.8219462}}, {"code": "P145", "value": "Naples", "coordinates": {"lat": 26.1420358, "lng": -81.7948103}}, {"code": "P146", "value": "Nassau", "coordinates": {"lat": 25.0443312, "lng": -77.3503609}}, {"code": "P147", "value": "New Delhi", "coordinates": {"lat": 28.6139391, "lng": 77.2090212}}, {"code": "P148", "value": "Niamey", "coordinates": {"lat": 13.5115963, "lng": 2.1253854}}, {"code": "P149", "value": "Nicosia", "coordinates": {"lat": 35.1855659, "lng": 33.38227639999999}}, {"code": "P150", "value": "Nogales", "coordinates": {"lat": 31.3403775, "lng": -110.9342532}}, {"code": "P151", "value": "Nouakchott", "coordinates": {"lat": 18.0735299, "lng": -15.9582372}}, {"code": "P152", "value": "Nuevo Laredo", "coordinates": {"lat": 27.4779362, "lng": -99.549573}}, {"code": "P153", "value": "Osaka-Kobe", "coordinates": {"lat": 34.6937249, "lng": 135.5022535}}, {"code": "P154", "value": "Oslo", "coordinates": {"lat": 59.9138688, "lng": 10.7522454}}, {"code": "P155", "value": "Ottawa", "coordinates": {"lat": 45.4215296, "lng": -75.69719309999999}}, {"code": "P156", "value": "Ouagadougou", "coordinates": {"lat": 12.3714277, "lng": -1.5196603}}, {"code": "P157", "value": "Panama City", "coordinates": {"lat": 30.1588129, "lng": -85.6602058}}, {"code": "P158", "value": "Paramaribo", "coordinates": {"lat": 5.8520355, "lng": -55.2038278}}, {"code": "P159", "value": "Paris", "coordinates": {"lat": 48.856614, "lng": 2.3522219}}, {"code": "P160", "value": "Perth", "coordinates": {"lat": -31.9523123, "lng": 115.861309}}, {"code": "P161", "value": "Phnom Penh", "coordinates": {"lat": 11.5563738, "lng": 104.9282099}}, {"code": "P162", "value": "Podgorica", "coordinates": {"lat": 42.4304196, "lng": 19.2593642}}, {"code": "P164", "value": "Port Au Prince", "coordinates": {"lat": 18.594395, "lng": -72.3074326}}, {"code": "P165", "value": "Port Louis", "coordinates": {"lat": -20.1608912, "lng": 57.5012222}}, {"code": "P166", "value": "Port Moresby", "coordinates": {"lat": -9.443800399999999, "lng": 147.1802671}}, {"code": "P167", "value": "Port Of Spain", "coordinates": {"lat": 10.6603196, "lng": -61.5085625}}, {"code": "porto_alegre", "value": "Porto Alegre", "coordinates": {"lat": -30.0368176, "lng": -51.2089887}}, {"code": "P168", "value": "Prague", "coordinates": {"lat": 50.0755381, "lng": 14.4378005}}, {"code": "P169", "value": "Praia", "coordinates": {"lat": 14.93305, "lng": -23.5133267}}, {"code": "P231", "value": "Pristina", "coordinates": {"lat": 42.6629138, "lng": 21.1655028}}, {"code": "P170", "value": "Quebec", "coordinates": {"lat": 46.8130816, "lng": -71.20745959999999}}, {"code": "P171", "value": "Quito", "coordinates": {"lat": -0.1806532, "lng": -78.4678382}}, {"code": "P172", "value": "Rangoon", "coordinates": {"lat": 16.840939, "lng": 96.173526}}, {"code": "P173", "value": "Recife", "coordinates": {"lat": -8.0577401, "lng": -34.8829629}}, {"code": "P174", "value": "Reykjavik", "coordinates": {"lat": 64.146582, "lng": -21.9426354}}, {"code": "P175", "value": "Riga", "coordinates": {"lat": 56.9676941, "lng": 24.1056221}}, {"code": "P230", "value": "Rio De Janeiro", "coordinates": {"lat": -22.9068467, "lng": -43.1728965}}, {"code": "P177", "value": "Riyadh", "coordinates": {"lat": 24.7135517, "lng": 46.6752957}}, {"code": "P178", "value": "Rome", "coordinates": {"lat": 41.9027835, "lng": 12.4963655}}, {"code": "P179", "value": "San Jose", "coordinates": {"lat": 37.33874, "lng": -121.8852525}}, {"code": "P180", "value": "San Salvador", "coordinates": {"lat": 13.6929403, "lng": -89.2181911}}, {"code": "P181", "value": "Sanaa", "coordinates": {"lat": 15.3694451, "lng": 44.1910066}}, {"code": "P182", "value": "Santiago", "coordinates": {"lat": -33.4488897, "lng": -70.6692655}}, {"code": "P183", "value": "Santo Domingo", "coordinates": {"lat": 18.4860575, "lng": -69.93121169999999}}, {"code": "P184", "value": "Sao Paulo", "coordinates": {"lat": -23.5557714, "lng": -46.6395571}}, {"code": "P224", "value": "Sapporo", "coordinates": {"lat": 43.0617713, "lng": 141.3544506}}, {"code": "P185", "value": "Sarajevo", "coordinates": {"lat": 43.8562586, "lng": 18.4130763}}, {"code": "P186", "value": "Seoul", "coordinates": {"lat": 37.566535, "lng": 126.9779692}}, {"code": "P187", "value": "Shanghai", "coordinates": {"lat": 31.230416, "lng": 121.473701}}, {"code": "P188", "value": "Shenyang", "coordinates": {"lat": 41.804778, "lng": 123.432968}}, {"code": "P189", "value": "Singapore", "coordinates": {"lat": 1.352083, "lng": 103.819836}}, {"code": "P190", "value": "Skopje", "coordinates": {"lat": 41.9981294, "lng": 21.4254355}}, {"code": "P191", "value": "Sofia", "coordinates": {"lat": 42.6977082, "lng": 23.3218675}}, {"code": "st_georges", "value": "St Georges", "coordinates": {"lat": 41.4909882, "lng": -71.2731677}}, {"code": "P192", "value": "St Petersburg", "coordinates": {"lat": 27.7676008, "lng": -82.64029149999999}}, {"code": "P193", "value": "Stockholm", "coordinates": {"lat": 59.32932349999999, "lng": 18.0685808}}, {"code": "P194", "value": "Surabaya", "coordinates": {"lat": -7.2574719, "lng": 112.7520883}}, {"code": "P195", "value": "Suva", "coordinates": {"lat": -18.1405049, "lng": 178.4232507}}, {"code": "P196", "value": "Sydney", "coordinates": {"lat": -33.8688197, "lng": 151.2092955}}, {"code": "P197", "value": "Taipei", "coordinates": {"lat": 25.0329636, "lng": 121.5654268}}, {"code": "P198", "value": "Tallinn", "coordinates": {"lat": 59.43696079999999, "lng": 24.7535746}}, {"code": "P199", "value": "Tashkent", "coordinates": {"lat": 41.2994958, "lng": 69.2400734}}, {"code": "P200", "value": "Tbilisi", "coordinates": {"lat": 41.7151377, "lng": 44.827096}}, {"code": "P201", "value": "Tegucigalpa", "coordinates": {"lat": 14.065049, "lng": -87.1715002}}, {"code": "P202", "value": "Tel Aviv", "coordinates": {"lat": 32.0852999, "lng": 34.78176759999999}}, {"code": "tijuana", "value": "Tijuana", "coordinates": {"lat": 32.5149469, "lng": -117.0382471}}, {"code": "P203", "value": "Tijuana Tpf", "coordinates": {"lat": 32.5149469, "lng": -117.0382471}}, {"code": "P204", "value": "Tirana", "coordinates": {"lat": 41.3275459, "lng": 19.8186982}}, {"code": "P205", "value": "Tokyo", "coordinates": {"lat": 35.6761919, "lng": 139.6503106}}, {"code": "P206", "value": "Toronto", "coordinates": {"lat": 43.653226, "lng": -79.3831843}}, {"code": "P207", "value": "Tripoli", "coordinates": {"lat": 32.8872094, "lng": 13.1913383}}, {"code": "P208", "value": "Tunis", "coordinates": {"lat": 36.8064948, "lng": 10.1815316}}, {"code": "P209", "value": "Ulaanbaatar", "coordinates": {"lat": 47.88639879999999, "lng": 106.9057439}}, {"code": "usun-new_york", "value": "Usun-New York", "coordinates": {"lat": 40.7127753, "lng": -74.0059728}}, {"code": "P210", "value": "Valletta", "coordinates": {"lat": 35.8989085, "lng": 14.5145528}}, {"code": "P211", "value": "Vancouver", "coordinates": {"lat": 49.2827291, "lng": -123.1207375}}, {"code": "P212", "value": "Vienna", "coordinates": {"lat": 48.2081743, "lng": 16.3738189}}, {"code": "P213", "value": "Vientiane", "coordinates": {"lat": 17.9757058, "lng": 102.6331035}}, {"code": "P214", "value": "Vilnius", "coordinates": {"lat": 54.6871555, "lng": 25.2796514}}, {"code": "P215", "value": "Vladivostok", "coordinates": {"lat": 43.1332484, "lng": 131.9112975}}, {"code": "P216", "value": "Warsaw", "coordinates": {"lat": 52.2296756, "lng": 21.0122287}}, {"code": "P217", "value": "Windhoek", "coordinates": {"lat": -22.5608807, "lng": 17.0657549}}, {"code": "P218", "value": "Yaounde", "coordinates": {"lat": 3.8480325, "lng": 11.5020752}}, {"code": "yekaterinburg", "value": "Yekaterinburg", "coordinates": {"lat": 56.8430993, "lng": 60.64540859999999}}, {"code": "P220", "value": "Yerevan", "coordinates": {"lat": 40.1872023, "lng": 44.515209}}, {"code": "P221", "value": "Zagreb", "coordinates": {"lat": 45.8150108, "lng": 15.981919}}]